Workbook

Sheet sales_analysis
A1: orderid | B1: product | C1: region | D1: salesperson | E1: units | F1: unit_price | G1: discount | H1: Gross sales | I1: Discount Amount | J1: net sales | K1: Tax amount | L1: final sales | M1: profi est | N1: profit margin
A2: DM 1001 | B2: rice | C2: east | D2: ravi | E2: 10 | F2: 500 | G2: 0.05 | H2: =(E2)*(F2) -> 5000 | I2: =(H2)*(G2) -> 250 | J2: =H2-I2 -> 4750 | K2: =J2*18% -> 855 | L2: =J2+K2 -> 5605 | M2: =J2-H2*70% -> 1250 | N2: =M2/J2 -> 0.26315789
A3: DM 1002 | B3: oil | C3: west | D3: arun | E3: 15 | F3: 180 | G3: 0.1 | H3: =(E3)*(F3) -> 2700 | I3: =(H3)*(G3) -> 270 | J3: =H3-I3 -> 2430 | K3: =J3*18% -> 437.4 | L3: =J3+K3 -> 2867.4 | M3: =J3-H3*70% -> 540 | N3: =M3/J3 -> 0.22222222
A4: DM 1003 | B4: sugar | C4: north | D4: priya | E4: 20 | F4: 50 | G4: 0.05 | H4: =(E4)*(F4) -> 1000 | I4: =(H4)*(G4) -> 50 | J4: =H4-I4 -> 950 | K4: =J4*18% -> 171 | L4: =J4+K4 -> 1121 | M4: =J4-H4*70% -> 250 | N4: =M4/J4 -> 0.26315789
A5: 1004 | B5: rice | C5: south | D5: sneha | E5: 8 | F5: 500 | G5: 0 | H5: =(E5)*(F5) -> 4000 | I5: =(H5)*(G5) -> 0 | J5: =H5-I5 -> 4000 | K5: =J5*18% -> 720 | L5: =J5+K5 -> 4720 | M5: =J5-H5*70% -> 1200 | N5: =M5/J5 -> 0.3
A6: 1005 | B6: oil | C6: east | D6: ravi | E6: 12 | F6: 180 | G6: 0.08 | H6: =(E6)*(F6) -> 2160 | I6: =(H6)*(G6) -> 172.8 | J6: =H6-I6 -> 1987.2 | K6: =J6*18% -> 357.696 | L6: =J6+K6 -> 2344.896 | M6: =J6-H6*70% -> 475.2 | N6: =M6/J6 -> 0.23913043
A7: 1006 | B7: sugar | C7: west | D7: arun | E7: 25 | F7: 50 | G7: 0.05 | H7: =(E7)*(F7) -> 1250 | I7: =(H7)*(G7) -> 62.5 | J7: =H7-I7 -> 1187.5 | K7: =J7*18% -> 213.75 | L7: =J7+K7 -> 1401.25 | M7: =J7-H7*70% -> 312.5 | N7: =M7/J7 -> 0.26315789
A8: 1007 | B8: rice | C8: north | D8: priya | E8: 6 | F8: 500 | G8: 0.1 | H8: =(E8)*(F8) -> 3000 | I8: =(H8)*(G8) -> 300 | J8: =H8-I8 -> 2700 | K8: =J8*18% -> 486 | L8: =J8+K8 -> 3186 | M8: =J8-H8*70% -> 600 | N8: =M8/J8 -> 0.22222222
A9: 1008 | B9: oil | C9: south | D9: sneha | E9: 18 | F9: 180 | G9: 0.05 | H9: =(E9)*(F9) -> 3240 | I9: =(H9)*(G9) -> 162 | J9: =H9-I9 -> 3078 | K9: =J9*18% -> 554.04 | L9: =J9+K9 -> 3632.04 | M9: =J9-H9*70% -> 810 | N9: =M9/J9 -> 0.26315789
A10: 1009 | B10: sugar | C10: east | D10: ravi | E10: 30 | F10: 50 | G10: 0 | H10: =(E10)*(F10) -> 1500 | I10: =(H10)*(G10) -> 0 | J10: =H10-I10 -> 1500 | K10: =J10*18% -> 270 | L10: =J10+K10 -> 1770 | M10: =J10-H10*70% -> 450 | N10: =M10/J10 -> 0.3
A11: 1010 | B11: rice | C11: west | D11: priya | E11: 14 | F11: 500 | G11: 0.08 | H11: =(E11)*(F11) -> 7000 | I11: =(H11)*(G11) -> 560 | J11: =H11-I11 -> 6440 | K11: =J11*18% -> 1159.2 | L11: =J11+K11 -> 7599.2 | M11: =J11-H11*70% -> 1540 | N11: =M11/J11 -> 0.23913043

Sheet KPI
A1: Metric | B1: values
A2: Total sales | B2: =SUM(sales_analysis!J2:J11) -> 29022.7
A3: Mean sales | B3: =AVERAGE(sales_analysis!J2:J11) -> 2902.27
A4: max sales | B4: =MAX(sales_analysis!J2:J11) -> 6440
A5: lowest sales | B5: =MIN(sales_analysis!J2:J11) -> 950
A6: no of orders | B6: =COUNT(sales_analysis!J2:J11) -> 10
A7: no of orders (characters) | B7: =COUNTA(sales_analysis!A2:A11) -> 10
A8: TOTAL UNITS | B8: =SUM(sales_analysis!E1:E11) -> 158

Sheet Sheet3
A1: CUSTOMER NAME | B1: STORES | C1: CATEGORY _CUSTOMER | D1: PINCODE | E1: cust_id
A2: JOHN | B2: s1 | C2: regular | D2: 560062 | E2: =LEFT(A2,2)&B2&LEFT(C2,2)&RIGHT(D2,2) -> JOs1re62
A3: DAVID | B3: s2 | C3: loyal | D3: 560078 | E3: =LEFT(A3,2)&B3&LEFT(C3,2)&RIGHT(D3,2) -> DAs2lo78
A4: WICK | B4: s3 | C4: non_regular | D4: 560098 | E4: =LEFT(A4,2)&B4&LEFT(C4,2)&RIGHT(D4,2) -> WIs3no98
A5: SMITH | B5: s1 | C5: regular | D5: 560063 | E5: =LEFT(A5,2)&B5&LEFT(C5,2)&RIGHT(D5,2) -> SMs1re63
A6: EVA | B6: s2 | C6: loyal | D6: 560075 | E6: =LEFT(A6,2)&B6&LEFT(C6,2)&RIGHT(D6,2) -> EVs2lo75
A7: BECKHAM | B7: s3 | C7: non_regular | D7: 560043 | E7: =LEFT(A7,2)&B7&LEFT(C7,2)&RIGHT(D7,2) -> BEs3no43
A8: GORGE | B8: s1 | C8: regular | D8: 560001 | E8: =LEFT(A8,2)&B8&LEFT(C8,2)&RIGHT(D8,2) -> GOs1re01
A9: LILLY | B9: s2 | C9: loyal | D9: 560010 | E9: =LEFT(A9,2)&B9&LEFT(C9,2)&RIGHT(D9,2) -> LIs2lo10
A10: MARY | B10: s3 | C10: non_regular | D10: 560073 | E10: =LEFT(A10,2)&B10&LEFT(C10,2)&RIGHT(D10,2) -> MAs3no73

Sheet sheet 4
A1: region | B1: sales | C1: no of sales
A2: east | B2: =SUMIF(sales_analysis!C2:C11,"east",sales_analysis!J2:J11) -> 8237.2 | C2: =COUNTIF(sales_analysis!C2:C11,"east") -> 3
A3: west | B3: =SUMIF(sales_analysis!C2:C11,"west",sales_analysis!J2:J11) -> 10057.5 | C3: =COUNTIF(sales_analysis!C2:C11,"west") -> 3
A4: north | B4: =SUMIF(sales_analysis!C2:C11,"north",sales_analysis!J2:J11) -> 3650 | C4: =COUNTIF(sales_analysis!C2:C11,"north") -> 2
A5: south | B5: =SUMIF(sales_analysis!C2:C11,"south",sales_analysis!J2:J11) -> 7078 | C5: =COUNTIF(sales_analysis!C2:C11,"south") -> 2

Sheet sales persons analysis
A1: person | B1: sales | C1: incentive | D1: total sales of rice in east region | E1: count_eat_rice
A2: ravi | B2: =SUMIF(sales_analysis!D2:D11,"ravi",sales_analysis!J2:J11) -> 8237.2 | C2: =IF(B2>4000,B2*10%+B2) -> 9060.92 | D2: =SUMIFS(sales_analysis!J2:J11,sales_analysis!C2:C11,"east",sales_analysis!B2:B11,"rice") -> 4750 | E2: =COUNTIFS(sales_analysis!B2:B11,"rice",sales_analysis!C2:C11,"east") -> 1
A3: arun | B3: =SUMIF(sales_analysis!D2:D11,"arun",sales_analysis!J2:J11) -> 3617.5 | C3: =IF(B3>4000,B3*10%+B3) -> FALSE
A4: priya | B4: =SUMIF(sales_analysis!D2:D11,"priya",sales_analysis!J2:J11) -> 10090 | C4: =IF(B4>4000,B4*10%+B4) -> 11099
A5: sneha | B5: =SUMIF(sales_analysis!D2:D11,"sneha",sales_analysis!J2:J11) -> 7078 | C5: =IF(B5>4000,B5*10%+B5) -> 7785.8
